{
    "sources": [
        {
            "id": "4gamer",
            "name": "4Gamer.net",
            "url": "https://www.4gamer.net/",
            "rss": "https://www.4gamer.net/rss/index.xml",
            "type": "rss",
            "categories": [
                "game"
            ],
            "content_tags": [
                "game-news",
                "anime"
            ],
            "language": "ja",
            "update_frequency": "daily"
        },
        {
            "id": "akiba-blog",
            "name": "Akiba Blog",
            "url": "http://blog.livedoor.jp/geek/",
            "rss": "http://blog.livedoor.jp/geek/index.rdf",
            "type": "rss",
            "categories": [
                "cafe",
                "event",
                "figure"
            ],
            "content_tags": [
                "akihabara",
                "event",
                "figure"
            ],
            "language": "ja",
            "update_frequency": "daily"
        },
        {
            "id": "amiami-news",
            "name": "あみあみニュース",
            "url": "https://news.amiami.jp",
            "rss": "https://news.amiami.jp/feed",
            "type": "rss",
            "categories": [
                "figure",
                "cafe",
                "event"
            ],
            "content_tags": [
                "figure",
                "merchandise",
                "amiami"
            ],
            "language": "ja",
            "update_frequency": "daily"
        },
        {
            "id": "animatetimes",
            "name": "アニメイトタイムズ",
            "url": "https://www.animatetimes.com/",
            "rss": "https://www.animatetimes.com/feed/",
            "type": "rss",
            "categories": [
                "anime",
                "cafe",
                "event"
            ],
            "content_tags": [
                "anime-news",
                "merchandise",
                "animate"
            ],
            "language": "ja",
            "update_frequency": "daily"
        },
        {
            "id": "anime-eiga",
            "name": "アニメ映画.com",
            "url": "https://anime.eiga.com/news/",
            "rss": "https://anime.eiga.com/news/rss/",
            "type": "rss",
            "categories": [
                "anime",
                "event"
            ],
            "content_tags": [
                "anime-movie",
                "film",
                "anime-news"
            ],
            "language": "ja",
            "update_frequency": "daily"
        },
        {
            "id": "animejapan",
            "name": "AnimeJapan Official",
            "url": "https://www.anime-japan.jp/",
            "rss": null,
            "type": "scrape",
            "categories": [
                "event"
            ],
            "content_tags": [
                "anime-japan",
                "event",
                "exhibition"
            ],
            "language": "ja",
            "update_frequency": "weekly"
        },
        {
            "id": "collabo-cafe",
            "name": "Collabo Cafe",
            "url": "https://collabo-cafe.com",
            "rss": "https://collabo-cafe.com/feed/",
            "type": "scrape",
            "categories": [
                "cafe",
                "event"
            ],
            "content_tags": [
                "cafe",
                "collaboration",
                "event"
            ],
            "language": "ja",
            "update_frequency": "daily"
        },
        {
            "id": "collabo-cafe-com",
            "name": "コラボカフェ - アニメ・漫画・ゲームのコラボ情報一覧まとめ",
            "url": "https://collabo-cafe.com/",
            "rss": "https://collabo-cafe.com/feed/",
            "type": "rss",
            "categories": [
                "cafe"
            ],
            "content_tags": [
                "collabo-cafe-com"
            ],
            "language": "ja",
            "update_frequency": "daily"
        },
        {
            "id": "dengeki-hobby",
            "name": "電撃ホビーウェブ",
            "url": "https://hobby.dengeki.com/",
            "rss": "https://hobby.dengeki.com/feed/",
            "type": "rss",
            "categories": [
                "figure"
            ],
            "content_tags": [
                "hobby",
                "figure",
                "model-kit"
            ],
            "language": "ja",
            "update_frequency": "daily"
        },
        {
            "id": "dengeki-vtuber",
            "name": "Dengeki Online (VTuber special)",
            "url": "https://dengekionline.com/special/vtuber",
            "rss": null,
            "type": "scrape",
            "categories": [
                "vtuber"
            ],
            "content_tags": [
                "dengeki-vtuber"
            ],
            "language": "ja",
            "update_frequency": "daily"
        },
        {
            "id": "eeo-media",
            "name": "eeo today メディア",
            "url": "https://eeo.today/media/",
            "rss": null,
            "type": "scrape",
            "categories": [
                "cafe",
                "event",
                "figure"
            ],
            "content_tags": [
                "cafe",
                "collaboration",
                "merchandise"
            ],
            "language": "ja",
            "update_frequency": "daily"
        },
        {
            "id": "game-spark",
            "name": "最新ニュース・まとめ | Game*Spark - 国内・海外ゲーム情報サイト",
            "url": "https://www.gamespark.jp/article/",
            "rss": "https://www.gamespark.jp/rss20/index.rdf",
            "type": "rss",
            "categories": [
                "game"
            ],
            "content_tags": [
                "game-spark"
            ],
            "language": "ja",
            "update_frequency": "daily"
        },
        {
            "id": "gamemakers-jp-feed",
            "name": "gamemakers-jp-feed",
            "url": "https://gamemakers.jp/",
            "rss": "https://gamemakers.jp/feed/",
            "type": "rss",
            "categories": [
                "game"
            ],
            "content_tags": [
                "gamemakers-jp-feed"
            ],
            "language": "ja",
            "update_frequency": "daily"
        },
        {
            "id": "goodsmile",
            "name": "Good Smile Company Blog",
            "url": "https://www.goodsmile.info/ja/posts/category/information/date/",
            "rss": null,
            "type": "scrape",
            "categories": [
                "figure"
            ],
            "content_tags": [
                "figure",
                "merchandise",
                "good-smile"
            ],
            "language": "ja",
            "update_frequency": "daily"
        },
        {
            "id": "hobby-watch",
            "name": "HOBBY Watch",
            "url": "https://hobby.watch.impress.co.jp/",
            "rss": "https://hobby.watch.impress.co.jp/data/rss/1.0/hob/feed.rdf",
            "type": "rss",
            "categories": [
                "figure"
            ],
            "content_tags": [
                "hobby",
                "figure",
                "model-kit"
            ],
            "language": "ja",
            "update_frequency": "daily"
        },
        {
            "id": "moguravr",
            "name": "Mogura VR (MoguLive)",
            "url": "https://www.moguravr.com/",
            "rss": "https://www.moguravr.com/feed/",
            "type": "rss",
            "categories": [
                "vtuber"
            ],
            "content_tags": [
                "moguravr"
            ],
            "language": "ja",
            "update_frequency": "daily"
        },
        {
            "id": "natalie-anime",
            "name": "Comic Natalie / Anime Natalie",
            "url": "https://natalie.mu/comic",
            "rss": "https://natalie.mu/comic/feed/news",
            "type": "rss",
            "categories": [
                "anime"
            ],
            "content_tags": [
                "anime-news",
                "manga",
                "pop-culture"
            ],
            "language": "ja",
            "update_frequency": "daily"
        },
        {
            "id": "natalie-news",
            "name": "ナタリー（総合ニュース）",
            "url": "https://natalie.mu/news",
            "rss": "https://natalie.mu/news/feed/news",
            "type": "rss",
            "categories": [
                "anime",
                "event"
            ],
            "content_tags": [
                "anime-news",
                "pop-culture"
            ],
            "language": "ja",
            "update_frequency": "daily"
        },
        {
            "id": "nitroplus-blog",
            "name": "モットニトロ（スタッフブログ）",
            "url": "https://www.nitroplus.co.jp/staff/",
            "rss": "https://www.nitroplus.co.jp/staff/index.xml",
            "type": "rss",
            "categories": [
                "anime",
                "event"
            ],
            "content_tags": [
                "visual-novel",
                "behind-the-scenes",
                "nitroplus"
            ],
            "language": "ja",
            "update_frequency": "weekly"
        },
        {
            "id": "nitroplus-goods",
            "name": "ニトロプラス グッズ",
            "url": "https://www.nitroplus.co.jp/goods/",
            "rss": "https://www.nitroplus.co.jp/goods/index.xml",
            "type": "rss",
            "categories": [
                "figure"
            ],
            "content_tags": [
                "merchandise",
                "figure",
                "nitroplus"
            ],
            "language": "ja",
            "update_frequency": "weekly"
        },
        {
            "id": "nitroplus-news",
            "name": "ニトロプラス 最新ニュース",
            "url": "https://www.nitroplus.co.jp/news/",
            "rss": "https://www.nitroplus.co.jp/news/index.xml",
            "type": "rss",
            "categories": [
                "anime",
                "event"
            ],
            "content_tags": [
                "visual-novel",
                "anime",
                "nitroplus"
            ],
            "language": "ja",
            "update_frequency": "weekly"
        },
        {
            "id": "prtimes-kotobukiya",
            "name": "PR TIMES（コトブキヤ）",
            "url": "https://prtimes.jp/main/html/searchrlp/company_id/74603",
            "rss": "https://prtimes.jp/companyrdf.php?company_id=74603",
            "type": "rss",
            "categories": [
                "figure",
                "event"
            ],
            "content_tags": [
                "figure",
                "kotobukiya",
                "merchandise"
            ],
            "language": "ja",
            "update_frequency": "weekly"
        }
    ]
}